[
  {
    "code": "CW",
    "label": "CW - Western redcedar",
    "description": "Western redcedar"
  },
  {
    "code": "DR",
    "label": "DR - Red alder",
    "description": "Red alder"
  },
  {
    "code": "EP",
    "label": "EP - Paper birch",
    "description": "Paper birch"
  },
  {
    "code": "FDC",
    "label": "FDC - Coastal Douglas-fir",
    "description": "Coastal Douglas-fir"
  },
  {
    "code": "FDI",
    "label": "FDI - Interior Douglas-fir",
    "description": "Interior Douglas-fir"
  },
  {
    "code": "HW",
    "label": "HW - Western hemlock",
    "description": "Western hemlock"
  },
  {
    "code": "LW",
    "label": "LW - Western larch",
    "description": "Western larch"
  },
  {
    "code": "PLI",
    "label": "PLI - Lodgepole pine",
    "description": "Lodgepole pine"
  },
  {
    "code": "PW",
    "label": "PW - Western white pine",
    "description": "Western white pine"
  },
  {
    "code": "PY",
    "label": "PY - Ponderosa pine",
    "description": "Ponderosa pine"
  },
  {
    "code": "SS",
    "label": "SS - Sitka spruce",
    "description": "Sitka spruce"
  },
  {
    "code": "SX",
    "label": "SX - Spruce hybrid",
    "description": "Spruce hybrid"
  }
]
